{"coordinateSystem":"Three.js world; +X right, +Y up, +Z forward.","screen":"ARENA","selectedBeastId":"chonkus","match":{"phase":"FIGHTING","timer":175.06},"player":{"name":"Chonkus","position":{"x":-2.1023361682891846,"y":0.6562531590461731,"z":-0.4312407970428467},"yaw":-2.63,"stamina":0.36,"mass":1,"attack":{"state":"COMMIT","profile":"blunt","chargeNorm":0.5222222222222221,"chargeTier":"ready","holdSeconds":0.47,"isBlocking":false}},"opponent":{"name":"Butterchonk","position":{"x":-1.0492124557495117,"y":0.21102146804332733,"z":-0.14498257637023926},"yaw":2.97,"stamina":0.64,"mass":0.99,"attack":{"state":"IDLE","profile":"shield","chargeNorm":0.044444444444444446,"chargeTier":"quick","holdSeconds":0.04,"isBlocking":false}},"controls":{"movement":"WASD","raisePrimary":"J","commitPrimary":"K","jump":"SPACE"},"recentDamageEvents":[{"source":"passive","segment":"hip_fr","amount":0.005,"splashText":"GLANCE!","age":1.174099999904632},{"source":"passive","segment":"ankle_fr","amount":0,"splashText":"GLANCE!","age":1.174099999904632},{"source":"passive","segment":"knee_r","amount":0.001,"splashText":"GLANCE!","age":1.174099999904632},{"source":"passive","segment":"ankle_l","amount":0.001,"splashText":"GLANCE!","age":1.174099999904632},{"source":"active","segment":"ankle_bl","amount":17.449,"profile":"blunt","splashText":"GLANCE!","age":1.174099999904632},{"source":"passive","segment":"shoulder_l","amount":0.011,"splashText":"GLANCE!","age":1.0975000000000001},{"source":"passive","segment":"torso_rear","amount":0.017,"splashText":"GLANCE!","age":1.0975000000000001},{"source":"passive","segment":"shoulder_l","amount":0.022,"splashText":"GLANCE!","age":1.0975000000000001},{"source":"passive","segment":"ankle_bl","amount":0.032,"splashText":"GLANCE!","age":1.0975000000000001},{"source":"passive","segment":"shoulder_l","amount":0.001,"splashText":"GLANCE!","age":1.02289999985695},{"source":"passive","segment":"knee_bl","amount":0.002,"splashText":"GLANCE!","age":1.02289999985695},{"source":"passive","segment":"shoulder_l","amount":0.032,"splashText":"GLANCE!","age":1.02289999985695}]}